perseus_client/__init__.py
perseus_client/client.py
perseus_client/config.py
perseus_client/exceptions.py
perseus_client/models.py
perseus_client/services/__init__.py
perseus_client/services/base_service.py
perseus_client/services/file_service.py
perseus_client/services/job_service.py
perseus_client/services/neo4j_service.py
perseus_client/services/ontology_service.py
perseus_client-1.0.0rc3.dist-info/METADATA
perseus_client-1.0.0rc3.dist-info/WHEEL
perseus_client-1.0.0rc3.dist-info/licenses/LICENSE
perseus_client-1.0.0rc3.dist-info/RECORD
