Metadata-Version: 2.4
Name: perseus-client
Version: 1.0.0rc3
Summary: A Python client for Perseus API
Project-URL: Homepage, https://github.com/pypa/sampleproject
Project-URL: Bug Tracker, https://github.com/pypa/sampleproject/issues
Author-email: Victor de La Salmonière <victor@lettria.com>
License-File: LICENSE
Classifier: License :: OSI Approved :: MIT License
Classifier: Operating System :: OS Independent
Classifier: Programming Language :: Python :: 3
Requires-Python: >=3.8
Requires-Dist: aiohttp
Requires-Dist: certifi
Requires-Dist: neo4j
Requires-Dist: pydantic
Requires-Dist: pydantic-settings
